MANIFEST.in
README.md
setup.py
docs/Tutorial.md
examples/hello.py
src/Gates.egg-info/PKG-INFO
src/Gates.egg-info/SOURCES.txt
src/Gates.egg-info/dependency_links.txt
src/Gates.egg-info/requires.txt
src/Gates.egg-info/top_level.txt
src/gates/__init__.py
src/gates/core/__init__.py
src/gates/core/application.py
src/gates/core/exceptions.py